{
    "id": "bukkehaugen-paa-blindern",
    "title": "Bukkehaugen på Blindern",
    "author": "Mathias Tjøtta Odden / Jon Steinmo Hernæs",
    "melody": "Jon Steinmo Hernæs",
    "event": "Bukkehaugsfestivalen 2016",
    "year": 2016,
    "lyrics": [
        [
            "Jeg vet om et sted som er vakkert og skjønt",
            "Der fuglene kvitrer og graset er grønt.",
            "Der elskere møtes og gir seg selv hen.",
            "Hvor Amors pil atter treffer igjen."
        ],
        [
            "Ved Blindern stasjon, opp en liten trase",
            "kan du fort skimte den nydelige",
            "varmen som treffer når du åpner en grind,",
            "der sommerkjoler flagrer i vind’"
        ],
        [
            "Refr:",
            "Bukkehaugen på Blindern!",
            "Kom igjen, la oss dra.",
            "Men vær lur, ikke etter snar,",
            "for Haugen gir, og den tar."
        ],
        [
            "Jeg husker en vår,  -  det var syttende mai.",
            "Jenta til gutten: « Du, jeg er så gla’i",
            "deg, men hva føler du egentlig for meg?»",
            "Gutten sa: «Unnskyld, det er meg, ikke deg»"
        ],
        [
            "Så var det en aften , litt lik den i kveld.",
            "Han kjente vel ingen, men kom likevel",
            "til å si hei til ei med sommerbrun  hud.",
            "Og jenta sa ja,  -   nå blir hun hans brud."
        ],
        [
            "Refr:",
            "Bukkehaugen på Blindern!",
            "Kom igjen, la oss dra.",
            "Men vær lur, ikke etter snar,",
            "for Haugen gir, og den tar."
        ],
        [
            "Når mørket omsider gjør sin dystre entre.",
            "Og folk tar til vettet og vandrer av sted.",
            "På jakt etter edel vin og Cointreau,",
            "på jakt etter en å varme seg på."
        ],
        [
            "Så ligger man der, både jente og gutt",
            "og vet at magien aldri tar slutt.",
            "For Haugen den står der i år etter år.",
            "Og før du får sagt det kommer atter en vår."
        ],
        [
            "Refr:",
            "Bukkehaugen på Blindern!",
            "Kom igjen, la oss dra.",
            "Men vær lur, ikke etter snar.",
            "For Haugen gir, og den tar.",
            "For Haugen gir, og den tar.",
            "For Haugen gir, og den tar."
        ]
    ],
    "comments": [],
    "start_page": 213,
    "end_page": 214
}