{
    "meta": {
        "id": "oekospoek",
        "title": "Økospøk",
        "author": "Espen Huldt-Nystrøm",
        "melody": "Espen Huldt-Nystrøm",
        "event": "Blindernrevyen 1975 ”Rampefeber”",
        "year": 1975,
        "comments": [],
        "start_page": 91,
        "end_page": 92,
        "youtube_link": "",
        "spotify_link": ""
    },
    "contents": [
        [
            {
                "type": "lyric",
                "text": "Jeg kommer og jeg går, "
            },
            {
                "type": "lyric",
                "text": "og jeg sier aldri når,"
            },
            {
                "type": "lyric",
                "text": "en farlig bi-person, "
            },
            {
                "type": "lyric",
                "text": "faktisk er jeg en demon"
            },
            {
                "type": "lyric",
                "text": "Og lurer du på hvem jeg er"
            },
            {
                "type": "lyric",
                "text": "så ta en bit av denne her..."
            }
        ],
        [
            {
                "type": "lyric",
                "text": "Jeg kommer og jeg går, "
            },
            {
                "type": "lyric",
                "text": "og jeg sier aldri når,"
            },
            {
                "type": "lyric",
                "text": "hvis frykten blir for stor, "
            },
            {
                "type": "lyric",
                "text": "se deg selv i speilet, bror!"
            },
            {
                "type": "lyric",
                "text": "Og føler du deg ekstra kvalm,"
            },
            {
                "type": "lyric",
                "text": "så er det svovel  -  og napalm..."
            }
        ],
        [
            {
                "type": "lyric",
                "text": "Jeg kommer og jeg går,"
            },
            {
                "type": "lyric",
                "text": "blir det også vår i år?"
            },
            {
                "type": "lyric",
                "text": "Husk solen stiger rød"
            },
            {
                "type": "lyric",
                "text": "selv når livets gnist er død."
            },
            {
                "type": "lyric",
                "text": "Akk, mange mennesker tror og spår,"
            },
            {
                "type": "lyric",
                "text": "men det er jeg som alltid rår!"
            }
        ],
        [
            {
                "type": "lyric",
                "text": "For jeg er et øko-spøko-spøkelse"
            },
            {
                "type": "lyric",
                "text": "Puster helst i eter, kullos,vakuum, damp og røkelse."
            },
            {
                "type": "lyric",
                "text": "Vil du knekke meg - selv om jeg visst kan være søt -"
            },
            {
                "type": "lyric",
                "text": "bør du hurtig legge hele hodet ditt i bløt."
            }
        ],
        [
            {
                "type": "lyric",
                "text": "For når jeg får no’n tusen tonn"
            },
            {
                "type": "lyric",
                "text": "med oljesøl på havets blanke vei,"
            },
            {
                "type": "lyric",
                "text": "da tar jeg knekken på hver jævla albatross"
            },
            {
                "type": "lyric",
                "text": "og hai og fesk og sei, tjo-hei!"
            },
            {
                "type": "lyric",
                "text": "Og får jeg satt i gang en diger atomkrig"
            },
            {
                "type": "lyric",
                "text": "med klampen helt i bånn..."
            },
            {
                "type": "lyric",
                "text": "da tar jeg knekken på hvert stikkelsbær "
            },
            {
                "type": "lyric",
                "text": "og fyr og tjei og husbanklån, -og sånn!"
            }
        ],
        [
            {
                "type": "lyric",
                "text": "Ja, jeg er øko-spøk for mange,"
            },
            {
                "type": "lyric",
                "text": "koser meg med en sigar, et lik, og en halv Lange."
            },
            {
                "type": "lyric",
                "text": "Yndlingssporten er å ryggsvømme i lunken tjære."
            },
            {
                "type": "lyric",
                "text": "Finner jeg en tjæretønne kan’ke jeg la være."
            },
            {
                "type": "lyric",
                "text": "Og får jeg gitt to biler til hver mann,"
            },
            {
                "type": "lyric",
                "text": "og bensin som er full av bly, "
            },
            {
                "type": "lyric",
                "text": "da har jeg automatisk knekket alt"
            },
            {
                "type": "lyric",
                "text": "som var igjen av rotter i hver by."
            },
            {
                "type": "lyric",
                "text": "Og får jeg fjernet moms og filter"
            },
            {
                "type": "lyric",
                "text": "fra den tjæretunge industri, "
            },
            {
                "type": "lyric",
                "text": "da tak jeg knekken på hver produsent"
            },
            {
                "type": "lyric",
                "text": "av menneskebarn og blomst og bi, hi, hi!"
            }
        ]
    ]
}